gridData/OpenDX.py
gridData/__init__.py
gridData/_version.py
gridData/core.py
gridData/gOpenMol.py
gridData/mrc.py
gridData/tests/__init__.py
gridData/tests/test_dx.py
gridData/tests/test_gOpenMol.py
gridData/tests/test_grid.py
gridData/tests/test_mrc.py
gridData/tests/datafiles/1jzv.ccp4
gridData/tests/datafiles/EMD-3001.map.bz2
gridData/tests/datafiles/__init__.py
gridData/tests/datafiles/nAChR_M2_water.plt
gridData/tests/datafiles/test.ccp4
gridData/tests/datafiles/test.dx
gridData/tests/datafiles/test.dx.gz
GridDataFormats-1.0.2.dist-info/AUTHORS
GridDataFormats-1.0.2.dist-info/COPYING
GridDataFormats-1.0.2.dist-info/COPYING.LESSER
GridDataFormats-1.0.2.dist-info/METADATA
GridDataFormats-1.0.2.dist-info/WHEEL
GridDataFormats-1.0.2.dist-info/top_level.txt
GridDataFormats-1.0.2.dist-info/zip-safe
GridDataFormats-1.0.2.dist-info/RECORD
