Metadata-Version: 2.1
Name: GridDataFormats
Version: 1.0.2
Summary: Reading and writing of data on regular grids in Python
Home-page: https://github.com/MDAnalysis/GridDataFormats
Download-URL: https://github.com/MDAnalysis/GridDataFormats/releases
Author: Oliver Beckstein
Author-email: orbeckst@gmail.com
License: LGPLv3
Keywords: science array density
Classifier: Development Status :: 6 - Mature
Classifier: Environment :: Console
Classifier: Intended Audience :: Science/Research
Classifier: License :: OSI Approved :: GNU Lesser General Public License v3 (LGPLv3)
Classifier: Operating System :: POSIX
Classifier: Operating System :: MacOS :: MacOS X
Classifier: Operating System :: Microsoft :: Windows 
Classifier: Programming Language :: Python
Classifier: Programming Language :: Python :: 3
Classifier: Programming Language :: Python :: 3.9
Classifier: Programming Language :: Python :: 3.10
Classifier: Programming Language :: Python :: 3.11
Classifier: Programming Language :: Python :: 3.12
Classifier: Topic :: Scientific/Engineering
Classifier: Topic :: Software Development :: Libraries :: Python Modules
Requires-Python: >=3.9
License-File: COPYING
License-File: COPYING.LESSER
License-File: AUTHORS
Requires-Dist: numpy>=1.21
Requires-Dist: scipy
Requires-Dist: mrcfile
